<?xml version="1.0" encoding="UTF-8"?>
<tour start="node3">
  <panorama id="node1">
    <input leveltilesize="510" levelingpitch="0" width="1500" leveltileurl="tiles/1/cf_%c/l_%l/c_%x/tile_%y.jpg" levelbiashidpi="0.400" levelingroll="0" height="1500" levelbias="0.400" overlap="1">
      <level width="1500" predecode="0" preload="0" height="1500"/>
      <level width="750" predecode="0" preload="0" height="750"/>
      <level width="375" predecode="1" preload="1" height="375"/>
      <preview color="0x808080" strip="1"/>
    </input>
    <view pannorth="0" fovmode="0">
      <start fov="70" pan="0" tilt="0"/>
      <min fov="5" pan="0" tilt="-90"/>
      <max fov="120" pan="360" tilt="90"/>
    </view>
    <userdata longitude="" comment="" title="" info="" description="" author="" datetime="" copyright="" source="" latitude="" tags="12.10.23"/>
    <hotspots width="180" wordwrap="1" height="20">
      <label width="180" backgroundcolor="0xffffff" borderalpha="1" wordwrap="1" background="1" border="1" backgroundalpha="1" height="20" textcolor="0x000000" textalpha="1" bordercolor="0x000000" enabled="1" borderradius="1"/>
      <polystyle backgroundcolor="0x0000ff" borderalpha="1" handcursor="1" backgroundalpha="0.2509803921568627" bordercolor="0x0000ff" mode="0"/>
      <hotspot title="" pan="176.3" description="" url="{node5}" id="Point01" skinid="ht_node" tilt="-6.41" target=""/>
      <hotspot title="" pan="133.08" description="" url="{node3}" id="Point02" skinid="ht_node" tilt="-4" target=""/>
    </hotspots>
    <media/>
    <transition softedge="0" zoomout="0" zoomin="0" blendtime="1" zoomfov="20" zoomspeed="2" enabled="0" zoomoutpause="1" type="crossdissolve" blendcolor="0x000000"/>
    <control lockedkeyboardzoom="0" contextfullscreen="0" sensitivity="8" lockedwheel="0" hideabout="0" invertwheel="0" invertcontrol="1" lockedmouse="0" speedwheel="1" dblclickfullscreen="0" lockedkeyboard="0" simulatemass="1"/>
  </panorama>
  <panorama id="node2">
    <input leveltilesize="510" levelingpitch="0" width="1500" leveltileurl="tiles/2/cf_%c/l_%l/c_%x/tile_%y.jpg" levelbiashidpi="0.400" levelingroll="0" height="1500" levelbias="0.400" overlap="1">
      <level width="1500" predecode="0" preload="0" height="1500"/>
      <level width="750" predecode="0" preload="0" height="750"/>
      <level width="375" predecode="1" preload="1" height="375"/>
      <preview color="0x808080" strip="1"/>
    </input>
    <view pannorth="0" fovmode="0">
      <start fov="70" pan="0" tilt="0"/>
      <min fov="5" pan="0" tilt="-90"/>
      <max fov="120" pan="360" tilt="90"/>
    </view>
    <userdata longitude="" comment="" title="" info="" description="" author="" datetime="" copyright="" source="" latitude="" tags="12.10.23"/>
    <hotspots width="180" wordwrap="1" height="20">
      <label width="180" backgroundcolor="0xffffff" borderalpha="1" wordwrap="1" background="1" border="1" backgroundalpha="1" height="20" textcolor="0x000000" textalpha="1" bordercolor="0x000000" enabled="1" borderradius="1"/>
      <polystyle backgroundcolor="0x0000ff" borderalpha="1" handcursor="1" backgroundalpha="0.2509803921568627" bordercolor="0x0000ff" mode="0"/>
      <hotspot title="" pan="-168.82" description="" url="{node4}" id="Point01" skinid="ht_node" tilt="-36.76" target=""/>
      <hotspot title="" pan="108.93" description="" url="{node3}" id="Point02" skinid="ht_node" tilt="-6.11" target=""/>
      <hotspot title="" pan="122.83" description="" url="{node5}" id="Point03" skinid="ht_node" tilt="-4.83" target=""/>
    </hotspots>
    <media/>
    <transition softedge="0" zoomout="0" zoomin="0" blendtime="1" zoomfov="20" zoomspeed="2" enabled="0" zoomoutpause="1" type="crossdissolve" blendcolor="0x000000"/>
    <control lockedkeyboardzoom="0" contextfullscreen="0" sensitivity="8" lockedwheel="0" hideabout="0" invertwheel="0" invertcontrol="1" lockedmouse="0" speedwheel="1" dblclickfullscreen="0" lockedkeyboard="0" simulatemass="1"/>
  </panorama>
  <panorama id="node3">
    <input leveltilesize="510" levelingpitch="0" width="1500" leveltileurl="tiles/3/cf_%c/l_%l/c_%x/tile_%y.jpg" levelbiashidpi="0.400" levelingroll="0" height="1500" levelbias="0.400" overlap="1">
      <level width="1500" predecode="0" preload="0" height="1500"/>
      <level width="750" predecode="0" preload="0" height="750"/>
      <level width="375" predecode="1" preload="1" height="375"/>
      <preview color="0x808080" strip="1"/>
    </input>
    <view pannorth="0" fovmode="0">
      <start fov="70" pan="0" tilt="0"/>
      <min fov="5" pan="0" tilt="-90"/>
      <max fov="120" pan="360" tilt="90"/>
    </view>
    <userdata longitude="" comment="" title="" info="" description="" author="" datetime="2023:10:13 08:48:37" copyright="" source="" latitude="" tags="12.10.23"/>
    <hotspots width="180" wordwrap="1" height="20">
      <label width="180" backgroundcolor="0xffffff" borderalpha="1" wordwrap="1" background="1" border="1" backgroundalpha="1" height="20" textcolor="0x000000" textalpha="1" bordercolor="0x000000" enabled="1" borderradius="1"/>
      <polystyle backgroundcolor="0x0000ff" borderalpha="1" handcursor="1" backgroundalpha="0.2509803921568627" bordercolor="0x0000ff" mode="0"/>
      <hotspot title="" pan="10.22" description="" url="{node4}" id="Point01" skinid="ht_node" tilt="-4.26" target=""/>
      <hotspot title="" pan="-90.41" description="" url="{node5}" id="Point02" skinid="ht_node" tilt="-11.45" target=""/>
      <hotspot title="" pan="-38.8" description="" url="{node1}" id="Point03" skinid="ht_node" tilt="-1.67" target=""/>
      <hotspot title="" pan="19.05" description="" url="{node2}" id="Point04" skinid="ht_node" tilt="0.13" target="-44.7902/-6.3291/70"/>
      <hotspot title="" pan="34.3" description="" url="{node6}" id="Point05" skinid="ht_node" tilt="-0.36" target=""/>
    </hotspots>
    <media/>
    <transition softedge="0" zoomout="0" zoomin="0" blendtime="1" zoomfov="20" zoomspeed="2" enabled="0" zoomoutpause="1" type="crossdissolve" blendcolor="0x000000"/>
    <control lockedkeyboardzoom="0" contextfullscreen="0" sensitivity="8" lockedwheel="0" hideabout="0" invertwheel="0" invertcontrol="1" lockedmouse="0" speedwheel="1" dblclickfullscreen="0" lockedkeyboard="0" simulatemass="1"/>
  </panorama>
  <panorama id="node4">
    <input leveltilesize="510" levelingpitch="0" width="1500" leveltileurl="tiles/4/cf_%c/l_%l/c_%x/tile_%y.jpg" levelbiashidpi="0.400" levelingroll="0" height="1500" levelbias="0.400" overlap="1">
      <level width="1500" predecode="0" preload="0" height="1500"/>
      <level width="750" predecode="0" preload="0" height="750"/>
      <level width="375" predecode="1" preload="1" height="375"/>
      <preview color="0x808080" strip="1"/>
    </input>
    <view pannorth="0" fovmode="0">
      <start fov="70" pan="0" tilt="0"/>
      <min fov="5" pan="0" tilt="-90"/>
      <max fov="120" pan="360" tilt="90"/>
    </view>
    <userdata longitude="" comment="" title="" info="" description="" author="" datetime="2023:10:13 08:50:36" copyright="" source="" latitude="" tags="12.10.23"/>
    <hotspots width="180" wordwrap="1" height="20">
      <label width="180" backgroundcolor="0xffffff" borderalpha="1" wordwrap="1" background="1" border="1" backgroundalpha="1" height="20" textcolor="0x000000" textalpha="1" bordercolor="0x000000" enabled="1" borderradius="1"/>
      <polystyle backgroundcolor="0x0000ff" borderalpha="1" handcursor="1" backgroundalpha="0.2509803921568627" bordercolor="0x0000ff" mode="0"/>
      <hotspot title="" pan="63.53" description="" url="{node2}" id="Point01" skinid="ht_node" tilt="-7.65" target="-51.4294/-8.34202/70"/>
      <hotspot title="" pan="128.45" description="" url="{node6}" id="Point02" skinid="ht_node" tilt="-4.84" target=""/>
      <hotspot title="" pan="161.62" description="" url="{node3}" id="Point03" skinid="ht_node" tilt="-7.51" target=""/>
      <hotspot title="" pan="-167.64" description="" url="{node5}" id="Point04" skinid="ht_node" tilt="-3.01" target=""/>
      <hotspot title="" pan="-106.38" description="" url="{node7}" id="Point05" skinid="ht_node" tilt="-0.08" target=""/>
    </hotspots>
    <media/>
    <transition softedge="0" zoomout="0" zoomin="0" blendtime="1" zoomfov="20" zoomspeed="2" enabled="0" zoomoutpause="1" type="crossdissolve" blendcolor="0x000000"/>
    <control lockedkeyboardzoom="0" contextfullscreen="0" sensitivity="8" lockedwheel="0" hideabout="0" invertwheel="0" invertcontrol="1" lockedmouse="0" speedwheel="1" dblclickfullscreen="0" lockedkeyboard="0" simulatemass="1"/>
  </panorama>
  <panorama id="node5">
    <input leveltilesize="510" levelingpitch="0" width="1500" leveltileurl="tiles/5/cf_%c/l_%l/c_%x/tile_%y.jpg" levelbiashidpi="0.400" levelingroll="0" height="1500" levelbias="0.400" overlap="1">
      <level width="1500" predecode="0" preload="0" height="1500"/>
      <level width="750" predecode="0" preload="0" height="750"/>
      <level width="375" predecode="1" preload="1" height="375"/>
      <preview color="0x808080" strip="1"/>
    </input>
    <view pannorth="0" fovmode="0">
      <start fov="70" pan="0" tilt="0"/>
      <min fov="5" pan="0" tilt="-90"/>
      <max fov="120" pan="360" tilt="90"/>
    </view>
    <userdata longitude="" comment="" title="" info="" description="" author="" datetime="2023:10:13 08:33:01" copyright="" source="" latitude="" tags="12.10.23"/>
    <hotspots width="180" wordwrap="1" height="20">
      <label width="180" backgroundcolor="0xffffff" borderalpha="1" wordwrap="1" background="1" border="1" backgroundalpha="1" height="20" textcolor="0x000000" textalpha="1" bordercolor="0x000000" enabled="1" borderradius="1"/>
      <polystyle backgroundcolor="0x0000ff" borderalpha="1" handcursor="1" backgroundalpha="0.2509803921568627" bordercolor="0x0000ff" mode="0"/>
      <hotspot title="" pan="1.37" description="" url="{node1}" id="Point01" skinid="ht_node" tilt="-2.73" target=""/>
      <hotspot title="" pan="61.89" description="" url="{node6}" id="Point02" skinid="ht_node" tilt="1.48" target=""/>
      <hotspot title="" pan="41.73" description="" url="{node2}" id="Point03" skinid="ht_node" tilt="1.94" target="-57.079/-0.792239/70"/>
      <hotspot title="" pan="85.77" description="" url="{node3}" id="Point04" skinid="ht_node" tilt="-9.09" target=""/>
    </hotspots>
    <media/>
    <transition softedge="0" zoomout="0" zoomin="0" blendtime="1" zoomfov="20" zoomspeed="2" enabled="0" zoomoutpause="1" type="crossdissolve" blendcolor="0x000000"/>
    <control lockedkeyboardzoom="0" contextfullscreen="0" sensitivity="8" lockedwheel="0" hideabout="0" invertwheel="0" invertcontrol="1" lockedmouse="0" speedwheel="1" dblclickfullscreen="0" lockedkeyboard="0" simulatemass="1"/>
  </panorama>
  <panorama id="node6">
    <input leveltilesize="510" levelingpitch="0" width="1500" leveltileurl="tiles/6/cf_%c/l_%l/c_%x/tile_%y.jpg" levelbiashidpi="0.400" levelingroll="0" height="1500" levelbias="0.400" overlap="1">
      <level width="1500" predecode="0" preload="0" height="1500"/>
      <level width="750" predecode="0" preload="0" height="750"/>
      <level width="375" predecode="1" preload="1" height="375"/>
      <preview color="0x808080" strip="1"/>
    </input>
    <view pannorth="0" fovmode="0">
      <start fov="70" pan="0" tilt="0"/>
      <min fov="5" pan="0" tilt="-90"/>
      <max fov="120" pan="360" tilt="90"/>
    </view>
    <userdata longitude="" comment="" title="" info="" description="" author="" datetime="" copyright="" source="" latitude="" tags="12.10.23"/>
    <hotspots width="180" wordwrap="1" height="20">
      <label width="180" backgroundcolor="0xffffff" borderalpha="1" wordwrap="1" background="1" border="1" backgroundalpha="1" height="20" textcolor="0x000000" textalpha="1" bordercolor="0x000000" enabled="1" borderradius="1"/>
      <polystyle backgroundcolor="0x0000ff" borderalpha="1" handcursor="1" backgroundalpha="0.2509803921568627" bordercolor="0x0000ff" mode="0"/>
      <hotspot title="" pan="-112.67" description="" url="{node4}" id="Point01" skinid="ht_node" tilt="-10.22" target=""/>
      <hotspot title="" pan="119.41" description="" url="{node3}" id="Point02" skinid="ht_node" tilt="-11.15" target=""/>
      <hotspot title="" pan="139.01" description="" url="{node5}" id="Point03" skinid="ht_node" tilt="-6.01" target=""/>
    </hotspots>
    <media/>
    <transition softedge="0" zoomout="0" zoomin="0" blendtime="1" zoomfov="20" zoomspeed="2" enabled="0" zoomoutpause="1" type="crossdissolve" blendcolor="0x000000"/>
    <control lockedkeyboardzoom="0" contextfullscreen="0" sensitivity="8" lockedwheel="0" hideabout="0" invertwheel="0" invertcontrol="1" lockedmouse="0" speedwheel="1" dblclickfullscreen="0" lockedkeyboard="0" simulatemass="1"/>
  </panorama>
  <panorama id="node7">
    <input leveltilesize="510" levelingpitch="0" width="1500" leveltileurl="tiles/16/cf_%c/l_%l/c_%x/tile_%y.jpg" levelbiashidpi="0.400" levelingroll="0" height="1500" levelbias="0.400" overlap="1">
      <level width="1500" predecode="0" preload="0" height="1500"/>
      <level width="750" predecode="0" preload="0" height="750"/>
      <level width="375" predecode="1" preload="1" height="375"/>
      <preview color="0x808080" strip="1"/>
    </input>
    <view pannorth="0" fovmode="0">
      <start fov="70" pan="0" tilt="0"/>
      <min fov="5" pan="0" tilt="-90"/>
      <max fov="120" pan="360" tilt="90"/>
    </view>
    <userdata longitude="" comment="" title="" info="" description="" author="" datetime="2023:10:26 21:46:35" copyright="" source="" latitude="" tags="19.09.23"/>
    <hotspots width="180" wordwrap="1" height="20">
      <label width="180" backgroundcolor="0xffffff" borderalpha="1" wordwrap="1" background="1" border="1" backgroundalpha="1" height="20" textcolor="0x000000" textalpha="1" bordercolor="0x000000" enabled="1" borderradius="1"/>
      <polystyle backgroundcolor="0x0000ff" borderalpha="1" handcursor="1" backgroundalpha="0.2509803921568627" bordercolor="0x0000ff" mode="0"/>
      <hotspot title="" pan="-80.76" description="" url="{node4}" id="Point01" skinid="ht_node" tilt="-3.12" target=""/>
    </hotspots>
    <media/>
    <transition softedge="0" zoomout="0" zoomin="0" blendtime="1" zoomfov="20" zoomspeed="2" enabled="0" zoomoutpause="1" type="crossdissolve" blendcolor="0x000000"/>
    <control lockedkeyboardzoom="0" contextfullscreen="0" sensitivity="8" lockedwheel="0" hideabout="0" invertwheel="0" invertcontrol="1" lockedmouse="0" speedwheel="1" dblclickfullscreen="0" lockedkeyboard="0" simulatemass="1"/>
  </panorama>
</tour>
